AlertManager/__init__.py
AlertManager/module.py
AlertManager-1.0.2.dist-info/LICENSE
AlertManager-1.0.2.dist-info/METADATA
AlertManager-1.0.2.dist-info/WHEEL
AlertManager-1.0.2.dist-info/top_level.txt
AlertManager-1.0.2.dist-info/RECORD
