Metadata-Version: 2.1
Name: AlertManager
Version: 1.0.2
Summary: AlertManager is an open-source Python library designed to streamline and enhance data validation processes for both local Pandas DataFrames and database tables.
Home-page: https://github.com/Qubdi/AlertManager
Author: Anri Tvalabeishvili, Kristine Dzneladze
Author-email: QubdiSolutions@gmail.com
Project-URL: Documentation, https://timeline-manager.readthedocs.io/en/latest/index.html
Project-URL: HomePage, https://github.com/Qubdi/AlertManager
Project-URL: Tracker, https://github.com/Qubdi/AlertManager/issues
Classifier: Programming Language :: Python :: 3
Classifier: License :: OSI Approved :: MIT License
Classifier: Operating System :: OS Independent
Requires-Python: >=3.6
License-File: LICENSE
Requires-Dist: SQLAlchemy (==1.4.39)
Requires-Dist: pandas
Requires-Dist: numpy
